sentimini/__init__.py
sentimini/core.py
sentimini/lexicon.py
sentimini-1.0.0.dist-info/METADATA
sentimini-1.0.0.dist-info/WHEEL
sentimini-1.0.0.dist-info/top_level.txt
sentimini-1.0.0.dist-info/RECORD
