Metadata-Version: 2.4
Name: sentimini
Version: 1.0.0
Summary: Tiny Sentiment Analyzer – rule-based & lexicon-based
Author: Mohammad Shohag
Project-URL: Homepage, https://github.com/shohagcsediu/sentimini
Keywords: sentiment-analysis,nlp,lightweight,polarity
Requires-Python: >=3.7
